boabem-0.3.0.dist-info/METADATA
boabem-0.3.0.dist-info/WHEEL
boabem-0.3.0.dist-info/licenses/LICENSE-APACHE
boabem-0.3.0.dist-info/licenses/LICENSE-MIT
boabem/__init__.py
boabem/boabem.abi3.so
boabem/boabem.pyi
boabem/py.typed
boabem-0.3.0.dist-info/RECORD
