Metadata-Version: 2.4
Name: boabem
Version: 0.3.0
Classifier: Programming Language :: Rust
Classifier: Programming Language :: JavaScript
Requires-Dist: hypothesis[pytest] ; extra == 'test'
Requires-Dist: pytest-pretty ; extra == 'test'
Requires-Dist: json-five ; extra == 'test'
Requires-Dist: deepdiff ; extra == 'test'
Provides-Extra: test
License-File: LICENSE-APACHE
License-File: LICENSE-MIT
Summary: Python bindings for the Rust crate 'boa', an embeddable JavaScript engine
Keywords: javascript,js
Author-email: Dowon <ks2515@naver.com>
License-Expression: MIT or Apache-2.0
Requires-Python: >=3.9
Project-URL: source, https://github.com/Bing-su/boabem
